rftoc.py
rftoc-0.0.3.dist-info/entry_points.txt
rftoc-0.0.3.dist-info/LICENSE
rftoc-0.0.3.dist-info/WHEEL
rftoc-0.0.3.dist-info/METADATA
rftoc-0.0.3.dist-info/RECORD
